ansibly/__init__.py
ansibly/ansibly.py
ansibly-0.0.4.dist-info/DESCRIPTION.rst
ansibly-0.0.4.dist-info/METADATA
ansibly-0.0.4.dist-info/RECORD
ansibly-0.0.4.dist-info/WHEEL
ansibly-0.0.4.dist-info/metadata.json
ansibly-0.0.4.dist-info/top_level.txt
